candid/__init__.py
candid/__version__.py
candid-0.0.0.dist-info/LICENSE
candid-0.0.0.dist-info/METADATA
candid-0.0.0.dist-info/WHEEL
candid-0.0.0.dist-info/top_level.txt
candid-0.0.0.dist-info/RECORD
