Metadata-Version: 2.1
Name: candid
Version: 0.0.0
Summary: Complete And Noiseless Distributions from Incomplete Data
Home-page: https://github.com/philastrophist/bayesian
Author: philastrophist
Author-email: shaun.c.read@gmail.com
License: MIT
Platform: UNKNOWN
Classifier: License :: OSI Approved :: MIT License
Classifier: Programming Language :: Python
Classifier: Programming Language :: Python :: 3
Classifier: Programming Language :: Python :: 3.3
Classifier: Programming Language :: Python :: 3.4
Classifier: Programming Language :: Python :: 3.5
Classifier: Programming Language :: Python :: 3.6
Classifier: Programming Language :: Python :: 3.7
Classifier: Programming Language :: Python :: Implementation :: CPython
Classifier: Programming Language :: Python :: Implementation :: PyPy
Requires-Dist: numpy
Requires-Dist: matplotlib
Requires-Dist: tqdm
Requires-Dist: scipy (==1.1.0)
Requires-Dist: scikit-learn (==0.19.1)
Requires-Dist: theano (==1.0.4)
Requires-Dist: h5py (==2.9.)
Requires-Dist: pymc3 (==3.4.1)
